flamapy/metamodels/smt_metamodel/__init__.py
flamapy/metamodels/smt_metamodel/models/__init__.py
flamapy/metamodels/smt_metamodel/models/pysmt_model.py
flamapy/metamodels/smt_metamodel/operations/__init__.py
flamapy/metamodels/smt_metamodel/operations/complete_config.py
flamapy/metamodels/smt_metamodel/operations/config_by_impact.py
flamapy/metamodels/smt_metamodel/operations/filter_configs.py
flamapy/metamodels/smt_metamodel/operations/maximize_impact.py
flamapy/metamodels/smt_metamodel/operations/minimize_impact.py
flamapy/metamodels/smt_metamodel/operations/number_of_products.py
flamapy/metamodels/smt_metamodel/operations/valid_config.py
flamapy/metamodels/smt_metamodel/operations/valid_model.py
flamapy/metamodels/smt_metamodel/transformations/__init__.py
flamapy/metamodels/smt_metamodel/transformations/graph_to_smt.py
flamapy/metamodels/smt_metamodel/utils/__init__.py
flamapy/metamodels/smt_metamodel/utils/config_sanitizer.py
flamapy_smt-1.3.9.dist-info/LICENSE.md
flamapy_smt-1.3.9.dist-info/METADATA
flamapy_smt-1.3.9.dist-info/WHEEL
flamapy_smt-1.3.9.dist-info/top_level.txt
flamapy_smt-1.3.9.dist-info/RECORD
