Metadata-Version: 2.1
Name: flamapy-smt
Version: 1.3.9
Summary: This repo host the SMT model concrete classes
Home-page: https://github.com/flamapy/smt_metamodel
Author: Antonio Germán Márquez Trujillo
Author-email: amtrujillo@us.es
Classifier: Programming Language :: Python :: 3
Classifier: License :: OSI Approved :: GNU General Public License v3 or later (GPLv3+)
Classifier: Operating System :: OS Independent
Requires-Python: >=3.10
License-File: LICENSE.md
Requires-Dist: z3-solver==4.14.1.0
Requires-Dist: flamapy==1.1.3
Requires-Dist: univers==30.12.1
